smart_scrapy/__init__.py
smart_scrapy/items.py
smart_scrapy-0.0.1.dist-info/METADATA
smart_scrapy-0.0.1.dist-info/WHEEL
smart_scrapy-0.0.1.dist-info/top_level.txt
smart_scrapy-0.0.1.dist-info/RECORD
