Metadata-Version: 2.1
Name: smart-scrapy
Version: 0.0.1
Summary: Smart Scrapy
Home-page: UNKNOWN
Author: amigcamel
Author-email: amigcamel@gmail.com
License: UNKNOWN
Platform: UNKNOWN
